{"ಹೊಱವಾಱು": [{"type": "noun", "defs": ["a sale made outside one's territory; a foreign sale.", "a duty or tax imposed on the goods sold outside one's territory."]}], "ಹೊಱವೊಳಲು": [{"type": "noun", "defs": ["the part or district situated on the outer side of the boundary (of a city); the outskirts."]}], "ಹೊಱಸು": [{"type": "noun", "defs": ["a kind of pigeon, whose entrance into the house, is considered inauspicious.", "Madana, a kind of bird.", "the greyish bird Francolinus pondicerianus of Phasianidae family, with red bill and legs, the francolin partridge.", "the bird Perdix rufus fabled to subsist upon moon-beams; Greek partridge.", "a kind of bird ( = small owl) supposed to give indication of what will happen in future.", "a kind of water-hen or gallinule, that both swim and wade.", "a person deserving to be despised; a despicable person."]}], "ಹೊಱಸೂಸು": [{"type": "verb", "defs": ["to send forth (liquid, light, heat, sound, particles, etc.); discharge; to emit.", "to become spread covering a wide area.", "to be expressed; to be made known.", "to express or make known.", "to cause to spread over a wide area."]}], "ಹೊಱಹಾಕು": [{"type": "verb", "defs": ["to put, push or throw out.", "to dismiss, sack (from a position, office, etc.)."]}], "ಹೊಱಹೊಮ್ಮಿಸು": [{"type": "verb", "defs": ["to cause to flow out.", "to make something to be seen, evident or obvious.", "to stretch something or cause to stretch out.", "to produce a sound (from a musical instrument).", "to cause to jump out or forward."]}], "ಹೊಱಹೊಮ್ಮು": [{"type": "verb", "defs": ["to flow out.", "to become seen or perceived; to appear; to become obvious.", "to become stretched out, extended or spread over.", "to be conducted in a grand manner.", "to take birth; to come into existence.", "to jump upward.", "to be streatched out or forward."]}], "ಹೊಱಹೊಱಡಿಸು": [{"type": "verb", "defs": ["to cause to come or go out (from within); to send out."]}], "ಹೊಱಹೊಱಡು": [{"type": "verb", "defs": ["to go out; to get out of."]}], "ಹೊಱಿಗೆ": [{"type": "noun", "defs": ["the act of carrying a load, burden on one's head or shoulders.", "that which is carried; a load; a burden.", "a burden carried on the head, shoulder, back, vehicle, etc.", "the condition, quality, fact or an instance of being responsible; an obligation; accountability; responsibility.", "an earnest attempt; an endeavour.", "a way, manner in which something is done or to be done.", "the quality of being available in plenty; abundance.", "anything that comes about as a consequence or outcome of some action, process, etc.; the effect or result.", "the quality or fact of being rigorous, harsh; rigour; severity.", "firm belief or confidence in the honesty, integrity, reliability, justice, etc. of another person or thing; faith; trust.", "a condition of great wretchedness or suffering because of pain, sorrow, poverty, etc.; distress; misery.", "the border of something (as a piece of land, village, nation, etc.)."]}, {"type": "noun", "defs": ["the act of protecting, guarding against danger, damager, ruin, etc."]}], "ಹೊಱಿಗೆಕಾಱ": [{"type": "noun", "defs": ["= ಹೊಱಿಗೆವಾಳ."]}], "ಹೊಱಿಗೆವಾಳ": [{"type": "noun", "defs": ["a man who carries load on his head or shoulder.", "a man who has or undertakes responsibility."]}], "ಹೊಱಿಸು": [{"type": "verb", "defs": ["to load a burden on; to place a lond on.", "to accuse; to charge with a blame.", "to entrust the responsibility (of something to)."]}], "ಹೊಱು": [{"type": "verb", "defs": ["to carry the burden on one's head, shoulder, back, etc.", "to wear, put on (on the body).", "to have; to get.", "to take up (to do); to undertake.", "to undergo successfully; to withstand; to endure.", "to take the responsibility of.", "to support one of the parties in a dispute, discussion, etc.", "to become a burden on (another).", "to own the responsibility of or get the blame for.", "(said of a woman) to have a young one developing in the womb; to be pregnant with.", "to owe (a debt, obligation, etc.).", "to make a solemn vow in the name of a god."]}], "ಹೊಱುಗಡೆ": [{"type": "noun", "defs": ["(arch.) a kind of tax."]}], "ಹೊಱೆ": [{"type": "noun", "defs": ["that which is carried; a load; a burden.", "a burden carried on the head, shoulder, back, vehicle, etc.", "that which is big is size.", "condition, quality, fact or instance of being responsible; an obligation; accountability; responsibility.", "a small bag, pouch for or a bundle of money.", "the quality of being available in plenty; abundance.", "thick, long hair of the head.", "a large quantity or number; a mass.", "(fig.) an unwanted person or responsibility (considered as a burden)."]}], "ಹೊಱೆಕಾಱ": [{"type": "noun", "defs": ["a man carrying a burden.", "a man who is responsible, accountable (for something)."]}], "ಹೊಱೆಗಟ್ಟು": [{"type": "verb", "defs": ["to make into a bundle; to wrap or tie together; to bundle."]}], "ಹೊಱೆಗಾಱ": [{"type": "noun", "defs": ["= ಹೊಱೆಕಾಱ."]}], "ಹೊಱೆತಲೆ": [{"type": "noun", "defs": ["a man having thick growth of hair on his scalp."]}], "ಹೊಱೆದಲೆ": [{"type": "noun", "defs": ["= ಹೊಱೆತಲೆ."]}], "ಹೊಱೆಯಾಳು": [{"type": "noun", "defs": ["a man or a servant, carrying a burden."]}], "ಹೋ": [{"type": "interjection", "defs": ["an interejection used to express wonder, pain, relief or is used for calling attention."]}], "ಹೋಕ": [{"type": "noun", "defs": ["he who wanders, roams; a wanderer.", "a man who spends time (idly).", "a cruel, wicked fellow.", "a dissolute, debauched man; a rake."]}], "ಹೋಕಾಯಂತ್ರ": [{"type": "noun", "defs": ["an instrument consisting of a magnetic needle, used for knowing the directions; a compass.", "a guiding person; a guide."]}], "ಹೋಕು": [{"type": "noun", "defs": ["the act of going out; departure; exit.", "the act of moving; a going; movement.", "a removal, curing (as of a disease).", "the quality or condition of being nothing or not existing; non-existence; nothingness."]}], "ಹೋಕುಳಿ": [{"type": "adjective", "defs": ["inclined or ready to quarrel, fight, make arguments; contentious; quarrelsome."]}, {"type": "noun", "defs": ["a man engaged in, tend to engage in, fighting.", "a physical struggle; a fight.", "an angry dispute or altercation; a disagreement marked by a temporary or permanent break in friendly relations; a quarrel.", "the action of opposing, resisting or combating; opposition.", "a vying of sexual partners in amorous sport.", "the quarrelsome bird; a peacock.", "the act or an instance of striking, as with the fist, a weapon or a hammer; a blow; a stroke."]}], "ಹೋಕುಳಿಸು": [{"type": "verb", "defs": ["to engage in battle or in single combat; attempt to defend oneself against or to subdue, defeat or destroy an adversary; to fight."]}], "ಹೋಕೆ": [{"type": "noun", "defs": ["= ಹೋಕು 1 & 2.", "a path, way or course.", "an action or plan to deceive, cheat, outwit, etc.; artifice; dodge; ruse; stratagem; a trick."]}], "ಹೋಕೆತನ": [{"type": "noun", "defs": ["the tendency of cheating or the quality of being a cheat."]}], "ಹೋಗಣಗಿಲು": [{"type": "noun", "defs": ["the plant Trianthema portulacastrum ( = T. monogyna, = T. obcordata) of Aizoaceae family."]}], "ಹೋಗಾಡಿಸು": [{"type": "verb", "defs": ["to suffer the loss of; to be deprived of; to lose.", "to inflict a loss; to deprive or to cause to lose."]}], "ಹೋಗಾಡು": [{"type": "verb", "defs": ["to spend without real gain, advantage; to waste.", "to fail in one's commitment; to fail to carry out one's promise.", "to leave permanently; to abandon.", "to get rid of or prevent from happenining; to eliminate.", "to pay off (the debt); to fulfil one's obligation."]}], "ಹೋಗಿಸು": [{"type": "verb", "defs": ["to cause to go from a place or leave for another place."]}], "ಹೋಗು": [{"type": "verb", "defs": ["to move from one place to another voluntarily; to go.", "to come to an end; to be over.", "to be removed; to be done away with; to be got rid off.", "to die or be destroyed.", "to go out of sight; to disappear.", "to go back; to return; to retreat.", "(a lamp, fire, etc.) to be put off, quenched.", "to happen; to be conducted (as an event).", "to have sexual intercourse; to have coition."]}, {"type": "noun", "defs": ["a departing or going away; departure.", "a missing or being deprived of.", "the act of expelling the waste matter from the bowels.", "a particular hold in wrestling."]}, {"type": "interjection", "defs": ["an interjection expressing one's dislike, dejection, etc.; 'get lost!'; 'go away!'."]}, {"type": "noun", "defs": ["a fire place giving out heat at two or more places so that food can be cooked in more than one vessels at a time."]}], "ಹೋಗುಎಳೆ": [{"type": "noun", "defs": ["the thread spread crosswise on the loom."]}], "ಹೋಗುಳು": [{"type": "noun", "defs": ["a beating; a blow; a heavy stroke."]}], "ಹೋಗೊಳಿಸು": [{"type": "verb", "defs": ["to let (someone or something) go."]}], "ಹೋಟಲು": [{"type": "noun", "defs": ["a place where tiffin, meals, beverages, etc. can be bought and eaten; a restaurant.", "a commercial establishment providing lodging and, usu. meals and other services for the public, esp. for travelers; a hotel."]}], "ಹೋಟಾರ": [{"type": "noun", "defs": ["a woody plant having many stems branching out low instead of one main stem or trunk; a shrub; a bush."]}], "ಹೋಟಿ": [{"type": "noun", "defs": ["the state or condition of being the same in power, value, rank, etc.; equality; parity.", "the act of competing, vying; competition.", "the act or process of adding two things or quantities together.", "a piece of wood, used to join other two pieces of wood."]}], "ಹೋಟಿಗ": [{"type": "noun", "defs": ["a man who enters into or being rivalry; a contender; a competitor."]}], "ಹೋಟೆ": [{"type": "noun", "defs": ["a hole or hollow in a rock or in the stem or big branch of a tree.", "a narrow, deep hole.", "that which is hollow.", "an empty, worthless thing.", "(dial.) sexual intercourse."]}, {"type": "noun", "defs": ["an animal or plant with the sexual organs of both the male and the female; a hemaphrodite.", "a person having both the male and female characteristics."]}], "ಹೋಟೆಲು": [{"type": "noun", "defs": ["= ಹೋಟಲು."]}], "ಹೋಟ್ಲು": [{"type": "noun", "defs": ["= ಹೋಟಲು."]}], "ಹೋಡ": [{"type": "noun", "defs": ["a small, open vessel or watercraft propelled by oars, paddles, sails or engine; a boat."]}], "ಹೋಡು": [{"type": "noun", "defs": ["the state or condition of being the same in power, value, rank, etc.; equality; parity."]}], "ಹೋತ": [{"type": "noun", "defs": ["a male of any of a genus (Capra) of wild or domesticated bovid ruminants with hollow horns; a he-goat."]}, {"type": "noun", "defs": ["= ಹೋತೃ -2."]}], "ಹೋತಕರಿ": [{"type": "noun", "defs": ["a man who is prospering."]}], "ಹೋತವ್ಯ": [{"type": "noun", "defs": ["an oblation given to a deity in a religious sacrifice."]}], "ಹೋತಾರ": [{"type": "noun", "defs": ["= ಹೋತೃ."]}], "ಹೋತು": [{"type": "noun", "defs": ["= ಹೋತ1."]}], "ಹೋತುದಱಿಹಿ": [{"type": "noun", "defs": ["he who chops or minces things into pieces; a mincer."]}], "ಹೋತೃ": [{"type": "noun", "defs": ["an offerer of an oblation in a sacrifice; a sacrificer.", "a priest who at a sacrifice invokes the gods or recites the Řg vedic hymns."]}], "ಹೋತೆ": [{"type": "noun", "defs": ["the plant Striga gesneroides ( = S. orobanchoides) of Scrophulariaceae family."]}], "ಹೋತ್ರ": [{"type": "noun", "defs": ["that which is offered as oblations in a sacrifice.", "the sacrifice itself."]}], "ಹೋತ್ರಿ": [{"type": "noun", "defs": ["= ಹೋತೃ - 1."]}], "ಹೋಪುರೆ": [{"type": "interjection", "defs": ["an interjection used in praising a performer; well done! bravo!."]}], "ಹೋಬಳಿ": [{"type": "noun", "defs": ["the way, path someone or something has moved on.", "the act, method, manner or course of proceeding in some action; esp., the sequence of steps to be followed; procedure."]}, {"type": "noun", "defs": ["a subdivision of a revenue district of a state.", "the chief town of such a division."]}], "ಹೋಬಳಿದಾರ": [{"type": "noun", "defs": ["the chief revenue officer of a hōbaḷi (subdivision of a district)."]}], "ಹೋಬ್ಳಿ": [{"type": "noun", "defs": ["= ಹೋಬಳಿ2."]}], "ಹೋಮ": [{"type": "noun", "defs": ["= ಹೋತ್ರ - 1.", "the act of offering oblations to a deity in a sacrifice.", "a living being that is sacrificed to propitiate a deity."]}], "ಹೋಮಂಗೊಳ್": [{"type": "verb", "defs": ["to be sacrificed; to be immolated."]}], "ಹೋಮಕುಂಡ": [{"type": "noun", "defs": ["a pit in the ground where sacrificial fire is maintained and to which sacrificial oblations are offered."]}], "ಹೋಮದ್ರವ್ಯ": [{"type": "noun", "defs": ["= ಹೋತ್ರ - 1."]}], "ಹೋಮಧೇನು": [{"type": "noun", "defs": ["a cow the milk of which is used only for purpose of religious sacrifices."]}], "ಹೋಮಾಗ್ನಿ": [{"type": "noun", "defs": ["the sacrificial fire."]}], "ಹೋಮಾತು": [{"type": "noun", "defs": ["an impractical saying."]}], "ಹೋಮಾನಲ": [{"type": "noun", "defs": ["= ಹೋಮಾಗ್ನಿ."]}], "ಹೋಮಿಯೋಪತಿ": [{"type": "noun", "defs": ["the method of treating diseases by drugs, given in minute doses, that would produce in a healthy person symptoms similar to those of the disease; homeopathy."]}], "ಹೋಮಿಸು": [{"type": "verb", "defs": ["to offer religiously oblations to a diety in a sacrifice.", "(fig.) to kill a person."]}], "ಹೋಮುಗಲ": [{"type": "noun", "defs": ["the plant Mentha pulegium of Lamiaceae family."]}], "ಹೋಮೆ": [{"type": "noun", "defs": ["the plant Tremaorientalis ( = Celtis orientalis) of Ulmaceae family."]}], "ಹೋಯಿ": [{"type": "independent clause", "defs": ["a lulling sound."]}], "ಹೋರ್": [{"type": "verb", "defs": ["= ಹೋರು1."]}, {"type": "noun", "defs": ["= ಹೋರು3."]}], "ಹೋರಟೆ": [{"type": "noun", "defs": ["= ಹೋರಾಟ."]}], "ಹೋರಟೆಗುಟ್ಟು": [{"type": "verb", "defs": ["(a fight, friction between two persons) to occur."]}], "ಹೋರಟೆಗೊಳ್": [{"type": "verb", "defs": ["= ಹೋರಾಡು."]}], "ಹೋರಟೆಗೊಳ್ಳು": [{"type": "verb", "defs": ["= ಹೋರಾಡು."]}], "ಹೋರಾಟ": [{"type": "noun", "defs": ["a battle or combat.", "an angry dispute or altercation; a disagreement marked by a temporary or permanent break in friendly relations; a quarrel.", "a discussion involving differing points of view; a debate; an argument.", "a task or goal requiring much effort to accomplish or achieve.", "a struggle for excelling; a competition."]}], "ಹೋರಾಟಗೆಯ್": [{"type": "verb", "defs": ["= ಹೋರಾಡು."]}], "ಹೋರಾಟಗೊಳ್": [{"type": "verb", "defs": ["= ಹೋರಾಡು."]}], "ಹೋರಾಡು": [{"type": "verb", "defs": ["to engage in a battle or in a single combat; to attempt to defend oneself against or to subdue, defeat or destroy an adversary; to fight.", "to contend in any manner; strive vigorously for or against something.", "to make great efforts or attempts; to strive; to struggle."]}], "ಹೋರಾಯಂತ್ರ": [{"type": "noun", "defs": ["any device used for measuring and indicating time; a clock or clock-like device."]}], "ಹೋರಾಶಾಸ್ತ್ರ": [{"type": "noun", "defs": ["the study that assumes and attempts to interpret the influence of the heavenly bodies on human affairs; astrology."]}], "ಹೋರಾಹೋರಿ": [{"type": "noun", "defs": ["the quality of being vehement or vigorous impetuosity."]}], "ಹೋರಾಳು": [{"type": "noun", "defs": ["a member of an army engaged in a fight; a soldier."]}], "ಹೋರಿ": [{"type": "noun", "defs": ["a young ox.", "an ox that is not castrated."]}], "ಹೋರಿಕ": [{"type": "noun", "defs": ["(masc.) an expert in astrology."]}], "ಹೋರಿಕೆ": [{"type": "noun", "defs": ["= ಹೋರಾಟ - 1 & 2."]}], "ಹೋರಿಗ": [{"type": "noun", "defs": ["= ಹೋರಿಕ."]}, {"type": "noun", "defs": ["a man in the service of another; a servant."]}], "ಹೋರಿಮಿಗ": [{"type": "noun", "defs": ["a male deer or antelope."]}], "ಹೋರಿಯಡೆ": [{"type": "noun", "defs": ["the excrement of a cow; cow-dung."]}], "ಹೋರಿಸು": [{"type": "verb", "defs": ["to cause to fight; to induce another to engage in or wage a war.", "to make another or others quarrel.", "to annoy, interfere with or meddle with so as to trouble or harm or with intent to trouble or harm."]}], "ಹೋರು": [{"type": "verb", "defs": ["to engage in battle or in single combat; attempt to defend oneself against or to subdue, defeat or destroy an adversary; to fight.", "to dispute heatedly; to quarrel.", "to rub oneself or one object against another.", "to struggle to excel another; to compete; to vie.", "to thrust with something (as horns of an ox, etc.).", "to argue; to debate; to dispute.", "to trouble; to vex.", "to make one's way with difficulty and great efforts."]}, {"type": "noun", "defs": ["= ಹೋರಾಟ."]}, {"type": "noun", "defs": ["a deep hole (as in the ground, etc.)."]}], "ಹೋರುಗಳೆ": [{"type": "verb", "defs": ["to make a hole; to bore or drill."]}], "ಹೋರುಗೆಡವು": [{"type": "verb", "defs": ["= ಹೋರುಗಳೆ."]}], "ಹೋರೆ": [{"type": "noun", "defs": ["= ಹೋರಾಶಾಸ್ತ್ರ.", "the rising of a zodiacal sign.", "one half of the duration of a sign.", "one twenty-forth part of a day; one hour."]}, {"type": "noun", "defs": ["that which chiefly engages one's time; (one's) trade, profession or business; occupation.", "a specific piece of work, as in one's trade or done by agreement for pay; a job.", "the state of being active; action; activity."]}, {"type": "noun", "defs": ["the tree Oroxylum indicum ( = Bignonia indica, = Calosanthes indica) of Bignoniaceae family."]}], "ಹೋರೆಗ": [{"type": "noun", "defs": ["= ಹೋರಿಕ."]}], "ಹೋರ್ಕೆ": [{"type": "noun", "defs": ["= ಹೋರಾಟ."]}], "ಹೋಲ್": [{"type": "noun", "defs": ["= ಹೋಲು1."]}], "ಹೋಲಿಕೆ": [{"type": "noun", "defs": ["the state of being similar; likeness; resemblance; similarity."]}], "ಹೋಲಿಸು": [{"type": "verb", "defs": ["to examine in order to observe or discover similarities or differences; to compare (with)."]}], "ಹೋಲು": [{"type": "verb", "defs": ["to be like another; to show resemblance; to be similar, alike."]}, {"type": "noun", "defs": ["a spending of money carelessly, unreasonably or unnecessarily; extravagance.", "a state or fact of being ruined.", "that which is worthless or useless."]}], "ಹೋಲುವೆ": [{"type": "noun", "defs": ["the state or quality of being similar; resemblance or likeness; similarity; parity.", "the quality of being lovely, charming; beauty; loveliness.", "the shape, outline or configuration of anything; structure; form."]}], "ಹೋಲ್ವೆ": [{"type": "noun", "defs": ["= ಹೋಲುವೆ."]}], "ಹೋವಣದಹಾಲೆ": [{"type": "noun", "defs": ["the plant Dregea volubilis ( = Marsdenia volubilis) of Asclepiadaceae family."]}], "ಹೋಷಿಯಾರ್": [{"type": "noun", "defs": ["the quality of being careful, thoughtful and cautious.", "keen intelligence; skill.", "absence of disease; health."]}], "ಹೋಸ": [{"type": "noun", "defs": ["(jain.) a practice of taking one's dinner before sunset or night advances."]}], "ಹೋಸಣ": [{"type": "noun", "defs": ["= ಹೋಸಳ."]}], "ಹೋಸಲ": [{"type": "noun", "defs": ["= ಹೋಸಳ."]}], "ಹೋಸಳ": [{"type": "noun", "defs": ["(correctly, ಹೋಯ್ಸಳ) one of the dynasties of Karnāṭaka, which ruled from Dōrasamudra (the present Haḷebīḍu)."]}], "ಹೋಸಾಲ": [{"type": "noun", "defs": ["= ಹೋಸಳ."]}], "ಹೋಹು": [{"type": "verb", "defs": ["to go near; to approach."]}, {"type": "noun", "defs": ["a way or method in which something is done or happens; mode or fashion of procedure."]}], "ಹೋಳ್": [{"type": "verb", "defs": ["= ಹೋಳು1."]}], "ಹೋಳಕ": [{"type": "noun", "defs": ["the grouse Pterochurus exnotus; a sand grouse."]}], "ಹೋಳಿ": [{"type": "noun", "defs": ["a paramour of Manmatha, the love-God.", "the spring festival at the approach of the vernal equinox.", "the coloured water sprinkled on each other during this festival.", "(fig.) the act of throwing (something on, away or out).", "the flame of a fire.", "that which is offered as oblation, sacrifice."]}], "ಹೋಳಿಗೆ": [{"type": "noun", "defs": ["a kind of flat, sweet cake made on a flat pan."]}, {"type": "noun", "defs": ["an inflamed, painful, pus-filled swelling on the skin, caused by localised infection; a furuncle; a boil."]}], "ಹೋಳಿಗೆವಡೆ": [{"type": "verb", "defs": ["to get boils, furncles on the skin."]}], "ಹೋಳಿಸು": [{"type": "verb", "defs": ["= ಹೋಳು1 - 1, 2 & 3."]}], "ಹೋಳಿಹಬ್ಬ": [{"type": "noun", "defs": ["= ಹೋಳಿ - 2."]}], "ಹೋಳು": [{"type": "verb", "defs": ["to cut into pieces.", "to split into two (vertically, lengthwise).", "to split (oneself) vertically into two pieces.", "to reduce to powder; to pulverise or pound.", "to destroy; to demolish.", "to be destroyed completely."]}, {"type": "noun", "defs": ["a piece cut from a bigger one or a whole; a fragment.", "an opening caused by or as if by splitting; a cleft, fissure or rift.", "a piece of areca nut."]}], "ಹೋಳುಗಡಿ": [{"type": "verb", "defs": ["to cut or chop into very small pieces; to mince."]}], "ಹೋಳುಗಳೆ": [{"type": "verb", "defs": ["= ಹೋಳು1."]}], "ಹೋಳುಗುಟ್ಟು": [{"type": "verb", "defs": ["to break or shatter into pieces with a heavy blow."]}], "ಹೌತ್ರ": [{"type": "noun", "defs": ["the function of a sacrificial priest."]}], "ಹೌದ": [{"type": "noun", "defs": ["= ಹೌದು2."]}, {"type": "noun", "defs": ["= ಹೌದಾ."]}], "ಹೌದಪ್ಪ": [{"type": "noun", "defs": ["a person who, regardless of actual attitude, always expresses agreement with his or her supervisor, superior, etc.; a sycophant; an yes-man.", "one who says 'yes' for everything without thinking independantly."]}], "ಹೌದಾ": [{"type": "noun", "defs": ["a seat, esp. with a canopy and railing, for riding on the back of an elephant; a howdah."]}], "ಹೌದು": [{"type": "independent clause", "defs": ["an affirmative expression; a term used to give one's agreement."]}, {"type": "noun", "defs": ["an artificial tank used for water storage."]}], "ಹೌದೆ": [{"type": "noun", "defs": ["= ಹೌದಾ."]}], "ಹೌರಿ": [{"type": "noun", "defs": ["(Muslim theology) any of a class of beautiful women in the paradise."]}], "ಹೌವನೆ": [{"type": "noun", "defs": ["accidentally; unexpectedly."]}], "ಹೌಸ": [{"type": "noun", "defs": ["(jain.) a practice of taking one's dinner before sunset or night advances."]}, {"type": "noun", "defs": ["= ಹೌಸು."]}], "ಹೌಸು": [{"type": "noun", "defs": ["energetic activity; stir; bustle; ferment.", "a strong desire."]}], "ಹೌಹಾರು": [{"type": "verb", "defs": ["to be disturbed or agitated suddenly as by alarm; to be startled."]}], "ಹೌಳಿಗೆ": [{"type": "noun", "defs": ["the large, deciduous tree Acrocarpus fraxinifolius of Caesalpinieae family."]}], "ಹ್ಯಸ್ತನ": [{"type": "adjective", "defs": ["of or belonging to, happened yesterday."]}], "ಹ್ಯಸ್ತನದಿನ": [{"type": "noun", "defs": ["the day before the current day; yesterday."]}], "ಹ್ಯಾಪ": [{"type": "noun", "defs": ["a dull-witted, stupid or ignorant man; a dolt; a dunce."]}], "ಹ್ಯಾಪು": [{"type": "noun", "defs": ["the quality of being stupid, ignorant; doltishness; stupidity."]}], "ಹ್ಯಾಪುಮೋರೆ": [{"type": "noun", "defs": ["a listless, spiritless face.", "a person being listless, spiritless."]}], "ಹ್ಯಾವ": [{"type": "noun", "defs": ["a shrinking from disgust; intense dislike or hatred; loathing; abhorrence.", "keen mental suffering; distress; grief.", "hatred; enmity; antagonism.", "intense anger; wrath; ire.", "the quality of being shy, bashful; shyness; bashfulness.", "proper respect for oneself and one's worth as a person; self-respect.", "the act of competing; rivalry; competition.", "a personally offensive act or word; deliberate act or display of disrespect; intentional slight; insult; affront.", "any departure from health; illness in general; disease.", "an inviting to come somewhere or do something.", "a stupid, slow-witted person; a blockhead; a dolt.", "a banner; a flag."]}], "ಹ್ರದ": [{"type": "noun", "defs": ["a place, in the course of a river, having a deep depression, and where water flows slowly.", "a deep lake.", "a ray of light."]}], "ಹ್ರದಿನಿ": [{"type": "noun", "defs": ["a stream or river.", "a flash of electric light; a lightning."]}], "ಹ್ರಸ್ವ": [{"type": "adjective", "defs": ["not extending far from end to end; not long or not long enough; short.", "little in size; small.", "very brief, requiring one unit of time (as a syllable) to be pronounced."]}, {"type": "noun", "defs": ["that which is short.", "anything that is small.", "a man of shorter in height, than normal men.", "(pros.) a short syllable."]}], "ಹ್ರಸ್ವಕಾಕು": [{"type": "noun", "defs": ["(pros.) a short vowel used at the end of a term used to address a person."]}], "ಹ್ರಸ್ವತೆ": [{"type": "noun", "defs": ["the quality of being short; shortness.", "the quality of being small; smallness.", "(pros.) the quality of a syllable being short."]}], "ಹ್ರಸ್ವಮತಿ": [{"type": "noun", "defs": ["the quality of not being sharp, keen (said of intelligence, grasping power, acumen, etc.).", "a person who lacks shrewdness, discernment, judgement, etc."]}], "ಹ್ರಸ್ವಸ್ವರ": [{"type": "noun", "defs": ["= ಹ್ರಸ್ವ2 - 4."]}], "ಹ್ರಸ್ವಾಕ್ಷರ": [{"type": "noun", "defs": ["= ಹ್ರಸ್ವ2 - 4."]}], "ಹ್ರಸ್ವಿ": [{"type": "noun", "defs": ["a kind of very small bird."]}], "ಹ್ರಾದ": [{"type": "noun", "defs": ["a sound; noise."]}], "ಹ್ರಾದಿನಿ": [{"type": "noun", "defs": ["a brilliant electric spark discharge in the atmosphere, occurring within a thundercloud, between clouds or between a cloud and the ground; a lightning.", "the thunder accompanying a flash of lightning; a thunderbolt.", "thunderbolt, as a weapon of Indra, the Lord of gods.", "a stream or river.", "the tree Boswellia serrata of Burseraceae family."]}], "ಹ್ರಾಸ": [{"type": "noun", "defs": ["a sound; noise.", "a becoming or growing less (gradually).", "scarcity; dearth; insufficiency; paucity."]}], "ಹ್ರ್ರಾಸನ": [{"type": "noun", "defs": ["the act or process of growing less."]}], "ಹ್ರಿದ್ದೇಶ": [{"type": "noun", "defs": ["the inner portion, region of anything.", "the mind, the inner faculty."]}], "ಹ್ರೀ": [{"type": "noun", "defs": ["the quality of being shy, bashful; shyness; bashfulness.", "name of one of the sixteen phases of the moon.", "(jain.) name of a goddess."]}], "ಹ್ರೀಂ": [{"type": "noun", "defs": ["one of the mystical syllables."]}], "ಹ್ರೀಂಕಾರಿ": [{"type": "noun", "defs": ["the goddess who is described by the mystical syllable \" hrīm \"."]}], "ಹ್ರೀಣ": [{"type": "adjective", "defs": ["shy; bashful."]}, {"type": "noun", "defs": ["a modest, bashful man."]}], "ಹ್ರೀತ": [{"type": "adjective", "defs": ["= ಹ್ರೀಣ1."]}, {"type": "noun", "defs": ["= ಹ್ರೀಣ2."]}], "ಹ್ರೀಬೇರ": [{"type": "noun", "defs": ["the fragrant root of the grass Vetiveria zizanioides ( = Andropogon muricatus) of the same family; vetiver."]}], "ಹ್ರೀವೇರ": [{"type": "noun", "defs": ["= ಹ್ರೀಬೇರ."]}], "ಹ್ರೇಷೆ": [{"type": "noun", "defs": ["the characteristic cry of a horse; a neigh; a whinny."]}], "ಹ್ಲಾದ": [{"type": "noun", "defs": ["joy; pleasure; gladness."]}], "ಹ್ಲಾದಿನಿ": [{"type": "noun", "defs": ["thunderbolt, as the weapon of Indra, the Lord of gods.", "the tree Boswellia serrata of Burseraceae family.", "a woman who delights.", "(Vaiṣṇava phil.) the divine love as one of the principles."]}], "ಳ": [{"type": "noun", "defs": ["(gen. pronounced with the vowel 'ಅ') the forty eighth letter of Kannaḍa alphabet and the thirty fourth consonant.", "(math.) a symbol for the number nine."]}], "ಳಕಾರ": [{"type": "noun", "defs": ["the letter or the sound of 'ಳ' (usu. pronounced with the vowel 'ಅ'."]}], "ಳತಾಂಗಿ": [{"type": "noun", "defs": ["a woman whose body is slender and delicate.", "a beautiful woman.", "(mus.) in Karnāṭaka system, the sixty third of the seventy two main modes."]}], "ಳತೆ": [{"type": "noun", "defs": ["any plant having a long, slender stem that trails or creeps on the ground or climbs by winding itself about a support or holding fast with tendrils or claspers; a vine; a creeper.", "(gen. ) a tender plant or tender part of a plant.", "a branch of a tree, shrub, etc.", "the grass Setaria italica ( = Panicum italicum) of Poaceae family.", "another grass Panicum dactylon of the same family.", "the vine Cardiospermum halicacabum of Sapindaceae family; heart pea.", "the plant Capparis brevispina of Capparaceae family.", "the plant Trigonella corniculata of Papilionaceae family.", "(jain.) a very long period (as an age or era).", "(dance.) the posture in which one arm is stretched straight and the hand is drooped loosely(?)."]}], "ಳತ್ವ": [{"type": "noun", "defs": ["= ಳಕಾರ."]}], "ಳಾಂತ": [{"type": "noun", "defs": ["a word that ends with the sound 'ಳ'."]}], "ಳಾಂತತೆ": [{"type": "noun", "defs": ["the fact of a word ending with the sound 'ಳ'."]}], "ಱ": [{"type": "noun", "defs": ["(gen. pronounced with the vowel 'ಅ') the forty ninth letter of Kannaḍa alphabet and the thirty fifth consonant."]}], "ಱಂಚಿಕೆ": [{"type": "noun", "defs": ["a seat, esp. with a canopy and railing, for riding on the back of an elephant; a howdah."]}, {"type": "noun", "defs": ["a kind of plant."]}], "ಱಂಚಿಗೆ": [{"type": "noun", "defs": ["= ಱಂಚಿಕೆ1."]}], "ಱಂಚೆ": [{"type": "noun", "defs": ["an armour to guard the sides of elephants or horses in the battlefield."]}], "ಱಂಚೆಯ": [{"type": "noun", "defs": ["= ಱಂಚೆ."]}], "ಱಂಜಿಕೆ": [{"type": "noun", "defs": ["= ಱಂಚಿಕೆ1."]}, {"type": "noun", "defs": ["= ಱಂಚಿಕೆ2."]}], "ಱಂಜಿಗೆ": [{"type": "noun", "defs": ["= ಱಂಚಿಕೆ2."]}], "ಱಕಾರ": [{"type": "noun", "defs": ["the letter or the sound of 'ಱ' (usu. pronounced with the vowel 'ಅ'."]}], "ಱಕ್ಕೆ": [{"type": "noun", "defs": ["either of the two feathered forelimbs of a bird, for flight, balance in running, for swimming, etc.; a wing.", "(dial.) that part of the human body between shoulder and elbow; the arm."]}], "ಱಚ್ಚೆ": [{"type": "noun", "defs": ["wet, soggy earth or something resembling this; slush; mire.", "the quality of being resentfully envious; envy; jealosy.", "the act of blaming; accusation; condemnation; censure.", "an act, condition, thing or person causing trouble, annoyance or inconvenience.", "the quality of being unyielding, obstinate; stubbornness; obstinacy.", "the act of revenging; vengeance; revenge.", "strong, stern or fierce anger; deeply resentful indignation; wrath; ire."]}], "ಱಚ್ಚೆಗೆಯ್": [{"type": "verb", "defs": ["to pursue something adamantly without heeding to any advice against it (as a child)."]}], "ಱಚ್ಚೆವಾತು": [{"type": "noun", "defs": ["a charge of wrongdoing; imputation of guilt or blame; accusation."]}], "ಱಟ್ಟಡಿ": [{"type": "noun", "defs": ["the verbal condemnation; harshly or coarsely insulting language; a scolding; abuse."]}], "ಱಟ್ಟಡಿಕಾತಿ": [{"type": "noun", "defs": ["a woman who uses harsh words or coarse language."]}], "ಱಟ್ಟಡಿಕಾರ್ತಿ": [{"type": "noun", "defs": ["= ಱಟ್ಟಡಿಕಾತಿ."]}], "ಱಟ್ಟಡಿಕಾಱ": [{"type": "noun", "defs": ["a man who uses harsh words or coarse language."]}], "ಱಟ್ಟಡಿತನ": [{"type": "noun", "defs": ["the quality of being harsh, hard, brave or adamant."]}], "ಱಟ್ಟೆ": [{"type": "noun", "defs": ["either of the two forelimbs of most birds and of bats that are specialised for flight; the wing.", "the part of the human body from shoulder to the wrist; the arm."]}], "ಱತ್ವ": [{"type": "noun", "defs": ["= ಱಕಾರ."]}], "ಱಪಱಪನೆ": [{"type": "adverb", "defs": ["with a sound as made by birds while flapping their wings.", "with a sound made by the heavy drops of rain falling rapidly.", "rapidly and repeatedly (as in beating)."]}], "ಱಪ್ಪು": [{"type": "noun", "defs": ["a fragment or piece taken out from a whole.", "brightness; shine; lustre.", "(fig.) a display of valour.", "an ostentatious display; pomp."]}], "ಱವಕೆ": [{"type": "noun", "defs": ["= ಱವಿಕೆ."]}], "ಱವಿಕೆ": [{"type": "noun", "defs": ["the upper garment of woman, covering the shoulders, back and breasts; a blouse.", "a protectivemade of metal and used in combat; an armour."]}], "ಱಳ": [{"type": "noun", "defs": ["= ಱೞ."]}], "ಱೞ": [{"type": "noun", "defs": ["the symbolic name with which \"ೞ\"."]}], "ಱೞಾಂತ": [{"type": "noun", "defs": ["any word or sound that ends with the letter or sound \"ೞ\"."]}], "ಱಾಂತ": [{"type": "noun", "defs": ["any word or sound that ends with the letter or sound \"ಱ\"."]}], "ಱಾಟಣ": [{"type": "noun", "defs": ["a small fixed wheel, sometimes turning in a block, with a grooved rim in which a rope or chain runs, as to raise a weight attached at one end by pulling on the other end; a pulley.", "a wheel, as a part of a machine.", "a circular, revolving platform with forms of animals as seats on it, used at carnivals, amusement parks, etc, operated by manual or electric power; a merry-go-round."]}], "ಱಾಟವಳ": [{"type": "noun", "defs": ["= ಱಾಟಣ."]}], "ಱಾಟಳ": [{"type": "noun", "defs": ["= ಱಾಟಣ."]}], "ಱಾಟಾಳ": [{"type": "noun", "defs": ["= ಱಾಟಣ."]}], "ಱಾಟ್ಟ": [{"type": "noun", "defs": ["= ಱಾಟಣ - 1 & 2.", "a spinning wheel."]}], "ಱಿಂಚೆಯ": [{"type": "noun", "defs": ["= ಱುಂಚೆ."]}], "ಱಿಕ್ಕಟ": [{"type": "adjective", "defs": ["having no worth or purpose; useless or unsatisfying; empty."]}, {"type": "noun", "defs": ["the quality of being empty; emptiness.", "absence of sound or a refraining from speaking."]}, {"type": "adverb", "defs": ["= ಱಿಕ್ಕಟಂ."]}], "ಱಿಕ್ಕಟಂ": [{"type": "adverb", "defs": ["without having a reason or purpose."]}], "ಱುಂಚೆ": [{"type": "noun", "defs": ["a sort of brazen drum."]}], "ಱುಂಜೆ": [{"type": "noun", "defs": ["= ಱುಂಚೆ."]}], "ಱೆಂಕೆ": [{"type": "noun", "defs": ["= ಱಕ್ಕೆ."]}], "ಱೆಂಚೆ": [{"type": "noun", "defs": ["= ಱಂಚೆ."]}], "ಱೆಂಚೆಯ": [{"type": "noun", "defs": ["= ಱಂಚೆ."]}], "ಱೆಕ್ಕೆ": [{"type": "noun", "defs": ["= ಱಕ್ಕೆ."]}], "ಱೆಪ್ಪು": [{"type": "verb", "defs": ["to hit or strike repeatedly; to pound; to beat.", "to throw or fling something at."]}], "ಱೆಪ್ಪೆ": [{"type": "noun", "defs": ["the movable lid of skin that serves to cover and uncover the front of the eyeball; the eyelid."]}], "ಱೊಂಕಿಡು": [{"type": "verb", "defs": ["= ಱೌಂಕಿಡು."]}], "ಱೊಂಕು": [{"type": "noun", "defs": ["= ಱೌಂಕು."]}], "ಱೊಂಪೆ": [{"type": "noun", "defs": ["wet, soft earth or earthy matter, as on the ground after rain, at the bottom of a pond or along the banks of a river; mire.", "offensive or disgusting dirt or refuse; foul matter; filth."]}], "ಱೊಜ್ಜು": [{"type": "noun", "defs": ["= ಱಚ್ಚೆ."]}], "ಱೊಟ್ಟು": [{"type": "noun", "defs": ["speed or vehemence of an action."]}], "ಱೊಟ್ಟುವಾಯ್": [{"type": "verb", "defs": ["to rush forward with force, vehemently."]}], "ಱೊಪ್ಪ": [{"type": "noun", "defs": ["the natural habitat of animals.", "a shelter or shed for animals, esp. for cattle, sheep, pig, etc.", "a house or a cluster of houses around such a shed.", "any loud and continued noise; clamour."]}], "ಱೊಪ್ಪಂಗೊಳ್": [{"type": "verb", "defs": ["to get a shelter; to be sheltered, protected."]}], "ಱೊಪ್ಪವಿಡಿ": [{"type": "verb", "defs": ["= ಱೊಪ್ಪಂಗೊಳ್."]}], "ಱೊಪ್ಪು": [{"type": "verb", "defs": ["to make indistinct sound or to utter harsh words, from anger."]}, {"type": "noun", "defs": ["= ಱೊಪ್ಪ."]}], "ಱೊಪ್ಪುಗೊಳ್": [{"type": "verb", "defs": ["= ಱೊಪ್ಪಂಗೊಳ್."]}], "ಱೊಬ್ಬು": [{"type": "noun", "defs": ["= ಱಪ್ಪು."]}], "ಱೊಬ್ಬೆ": [{"type": "noun", "defs": ["= ಱಪ್ಪು."]}, {"type": "noun", "defs": ["= ಱೊಂಪೆ."]}], "ಱೋಂಕಿಡು": [{"type": "noun", "defs": ["= ಱೌಂಕಿಡು."]}], "ಱೋಂಕು": [{"type": "noun", "defs": ["= ಱೌಂಕು."]}], "ಱೋಡಗ": [{"type": "noun", "defs": ["a professional fool or clown, esp. at a royal court; a jester.", "a man lacking normal intelligence; a fool; a stupid fellow.", "a shameless, immodest fellow."]}], "ಱೋಡಗತನ": [{"type": "noun", "defs": ["a deriding or being derided; contempt or ridicule; derision."]}], "ಱೋಡಗತನಂಗೆಯ್": [{"type": "verb", "defs": ["= ಱೋಡಾಡು."]}], "ಱೋಡಗವಂತ": [{"type": "noun", "defs": ["an immodest, shameless man."]}], "ಱೋಡಾಡಿಸು": [{"type": "verb", "defs": ["= ಱೋಡಾಡು."]}], "ಱೋಡಾಡು": [{"type": "verb", "defs": ["to make the object of scornful laughter; to make fun of; to deride; to ridicule."]}], "ಱೋಡಿಸು": [{"type": "verb", "defs": ["= ಱೋಡಾಡು."]}], "ಱೋಡು": [{"type": "verb", "defs": ["= ಱೋಡಾಡು."]}], "ಱೋಡೆಗ": [{"type": "noun", "defs": ["= ಱೋಡಗ."]}], "ಱೌಂಕಿಡು": [{"type": "verb", "defs": ["(a bull) to roar with a powerful, reverberating sound; to moo; to bellow.", "to utter such a sound or imitate it."]}], "ಱೌಂಕು": [{"type": "noun", "defs": ["the powerful, reverberating roaring sound made by a bull.", "a sound similar to this."]}], "ೞ": [{"type": "noun", "defs": ["(gen. pronounced with the vowel 'ಅ') the fiftieth letter of Kannaḍa alphabet and the thirty sixth consonant."]}], "ೞಕಾರ": [{"type": "noun", "defs": ["the letter or the sound of 'ೞ' (usu. pronounced with the vowel 'ಅ'."]}], "ೞತ್ವ": [{"type": "noun", "defs": ["= ೞಕಾರ."]}], "ೞಾಂತ": [{"type": "noun", "defs": ["a word that ends with the sound 'ೞ'."]}], "ೞಾಂತತೆ": [{"type": "noun", "defs": ["the fact of a word ending with the sound 'ೞ'."]}]}